taskbeat.py
taskbeat-0.1.1.dist-info/LICENSE
taskbeat-0.1.1.dist-info/METADATA
taskbeat-0.1.1.dist-info/WHEEL
taskbeat-0.1.1.dist-info/top_level.txt
taskbeat-0.1.1.dist-info/RECORD
