Metadata-Version: 2.1
Name: taskbeat
Version: 0.1.1
Summary: In memory task schedule support cron tasks, interval tasks and onetime tasks. Using python's asyncio.
Author: Chen Jia
Author-email: chenjia@zencore.cn
Maintainer: Chen Jia
Maintainer-email: chenjia@zencore.cn
License: MIT
Keywords: taskbeat
Classifier: Development Status :: 5 - Production/Stable
Classifier: Intended Audience :: Developers
Classifier: Topic :: Software Development :: Libraries :: Python Modules
Classifier: License :: OSI Approved :: MIT License
Classifier: Programming Language :: Python :: 3
Classifier: Programming Language :: Python :: 3 :: Only
Requires-Python: >=3.7
License-File: LICENSE
Requires-Dist: croniter
